{"assets/PFRegalTextPro-Bold.ttf":["assets/PFRegalTextPro-Bold.ttf"],"assets/PFRegalTextPro-BoldItalic.ttf":["assets/PFRegalTextPro-BoldItalic.ttf"],"assets/PFRegalTextPro-RegularB.ttf":["assets/PFRegalTextPro-RegularB.ttf"],"assets/PFRegalTextPro-RegularBItalic.ttf":["assets/PFRegalTextPro-RegularBItalic.ttf"],"assets/Proxima-Nova-Bold.ttf":["assets/Proxima-Nova-Bold.ttf"],"assets/Proxima-Nova-Regular.ttf":["assets/Proxima-Nova-Regular.ttf"],"assets/Proxima-Nova-Semibold.ttf":["assets/Proxima-Nova-Semibold.ttf"],"assets/icons/2x/banner_bg.png":["assets/icons/2x/banner_bg.png"],"assets/icons/2x/banner_thanks.png":["assets/icons/2x/banner_thanks.png"],"assets/icons/2x/bg_footnote-black.png":["assets/icons/2x/bg_footnote-black.png"],"assets/icons/2x/bg_footnote-light.png":["assets/icons/2x/bg_footnote-light.png"],"assets/icons/2x/bg_heaven_01.png":["assets/icons/2x/bg_heaven_01.png"],"assets/icons/2x/bg_heaven_01_black.png":["assets/icons/2x/bg_heaven_01_black.png"],"assets/icons/2x/bg_heaven_02.png":["assets/icons/2x/bg_heaven_02.png"],"assets/icons/2x/bg_heaven_02_black.png":["assets/icons/2x/bg_heaven_02_black.png"],"assets/icons/2x/bg_heaven_03.png":["assets/icons/2x/bg_heaven_03.png"],"assets/icons/2x/bg_heaven_03_black.png":["assets/icons/2x/bg_heaven_03_black.png"],"assets/icons/2x/bg_heaven_04.png":["assets/icons/2x/bg_heaven_04.png"],"assets/icons/2x/bg_heaven_04_black.png":["assets/icons/2x/bg_heaven_04_black.png"],"assets/icons/2x/bg_heaven_05.png":["assets/icons/2x/bg_heaven_05.png"],"assets/icons/2x/bg_heaven_05_black.png":["assets/icons/2x/bg_heaven_05_black.png"],"assets/icons/2x/bg_hell_01.png":["assets/icons/2x/bg_hell_01.png"],"assets/icons/2x/bg_hell_01_black.png":["assets/icons/2x/bg_hell_01_black.png"],"assets/icons/2x/bg_hell_02.png":["assets/icons/2x/bg_hell_02.png"],"assets/icons/2x/bg_hell_02_black.png":["assets/icons/2x/bg_hell_02_black.png"],"assets/icons/2x/bg_hell_03.png":["assets/icons/2x/bg_hell_03.png"],"assets/icons/2x/bg_hell_03_black.png":["assets/icons/2x/bg_hell_03_black.png"],"assets/icons/2x/bg_hell_04.png":["assets/icons/2x/bg_hell_04.png"],"assets/icons/2x/bg_hell_04_black.png":["assets/icons/2x/bg_hell_04_black.png"],"assets/icons/2x/bg_hell_05.png":["assets/icons/2x/bg_hell_05.png"],"assets/icons/2x/bg_hell_05_black.png":["assets/icons/2x/bg_hell_05_black.png"],"assets/icons/2x/bg_hell_AD_05.png":["assets/icons/2x/bg_hell_AD_05.png"],"assets/icons/2x/bg_hell_AD_05_black.png":["assets/icons/2x/bg_hell_AD_05_black.png"],"assets/icons/2x/bottom_splash.png":["assets/icons/2x/bottom_splash.png"],"assets/icons/2x/icon_15back-black.png":["assets/icons/2x/icon_15back-black.png"],"assets/icons/2x/icon_15back-light.png":["assets/icons/2x/icon_15back-light.png"],"assets/icons/2x/icon_15forward-black.png":["assets/icons/2x/icon_15forward-black.png"],"assets/icons/2x/icon_15forward-light.png":["assets/icons/2x/icon_15forward-light.png"],"assets/icons/2x/icon_UPS.png":["assets/icons/2x/icon_UPS.png"],"assets/icons/2x/icon_collapse.png":["assets/icons/2x/icon_collapse.png"],"assets/icons/2x/icon_footnote_arrow.png":["assets/icons/2x/icon_footnote_arrow.png"],"assets/icons/2x/icon_forward-black.png":["assets/icons/2x/icon_forward-black.png"],"assets/icons/2x/icon_forward-light.png":["assets/icons/2x/icon_forward-light.png"],"assets/icons/2x/icon_live-gold.png":["assets/icons/2x/icon_live-gold.png"],"assets/icons/2x/icon_live-red.png":["assets/icons/2x/icon_live-red.png"],"assets/icons/2x/icon_live-white.png":["assets/icons/2x/icon_live-white.png"],"assets/icons/2x/icon_ok-black.png":["assets/icons/2x/icon_ok-black.png"],"assets/icons/2x/icon_ok-light.png":["assets/icons/2x/icon_ok-light.png"],"assets/icons/2x/icon_profile.png":["assets/icons/2x/icon_profile.png"],"assets/icons/2x/icon_search.png":["assets/icons/2x/icon_search.png"],"assets/icons/2x/logo.png":["assets/icons/2x/logo.png"],"assets/icons/2x/story_logo-black.png":["assets/icons/2x/story_logo-black.png"],"assets/icons/2x/story_logo-light.png":["assets/icons/2x/story_logo-light.png"],"assets/icons/2x/top_splash.png":["assets/icons/2x/top_splash.png"],"assets/icons/3.5x/banner_bg.png":["assets/icons/3.5x/banner_bg.png"],"assets/icons/3.5x/banner_thanks.png":["assets/icons/3.5x/banner_thanks.png"],"assets/icons/3.5x/bg_footnote-black.png":["assets/icons/3.5x/bg_footnote-black.png"],"assets/icons/3.5x/bg_footnote-light.png":["assets/icons/3.5x/bg_footnote-light.png"],"assets/icons/3.5x/bg_heaven_01.png":["assets/icons/3.5x/bg_heaven_01.png"],"assets/icons/3.5x/bg_heaven_01_black.png":["assets/icons/3.5x/bg_heaven_01_black.png"],"assets/icons/3.5x/bg_heaven_02.png":["assets/icons/3.5x/bg_heaven_02.png"],"assets/icons/3.5x/bg_heaven_02_black.png":["assets/icons/3.5x/bg_heaven_02_black.png"],"assets/icons/3.5x/bg_heaven_03.png":["assets/icons/3.5x/bg_heaven_03.png"],"assets/icons/3.5x/bg_heaven_03_black.png":["assets/icons/3.5x/bg_heaven_03_black.png"],"assets/icons/3.5x/bg_heaven_04.png":["assets/icons/3.5x/bg_heaven_04.png"],"assets/icons/3.5x/bg_heaven_04_black.png":["assets/icons/3.5x/bg_heaven_04_black.png"],"assets/icons/3.5x/bg_heaven_05.png":["assets/icons/3.5x/bg_heaven_05.png"],"assets/icons/3.5x/bg_heaven_05_black.png":["assets/icons/3.5x/bg_heaven_05_black.png"],"assets/icons/3.5x/bg_hell_01.png":["assets/icons/3.5x/bg_hell_01.png"],"assets/icons/3.5x/bg_hell_01_black.png":["assets/icons/3.5x/bg_hell_01_black.png"],"assets/icons/3.5x/bg_hell_02.png":["assets/icons/3.5x/bg_hell_02.png"],"assets/icons/3.5x/bg_hell_02_black.png":["assets/icons/3.5x/bg_hell_02_black.png"],"assets/icons/3.5x/bg_hell_03.png":["assets/icons/3.5x/bg_hell_03.png"],"assets/icons/3.5x/bg_hell_03_black.png":["assets/icons/3.5x/bg_hell_03_black.png"],"assets/icons/3.5x/bg_hell_04.png":["assets/icons/3.5x/bg_hell_04.png"],"assets/icons/3.5x/bg_hell_04_black.png":["assets/icons/3.5x/bg_hell_04_black.png"],"assets/icons/3.5x/bg_hell_05.png":["assets/icons/3.5x/bg_hell_05.png"],"assets/icons/3.5x/bg_hell_05_black.png":["assets/icons/3.5x/bg_hell_05_black.png"],"assets/icons/3.5x/bg_hell_AD_05.png":["assets/icons/3.5x/bg_hell_AD_05.png"],"assets/icons/3.5x/bg_hell_AD_05_black.png":["assets/icons/3.5x/bg_hell_AD_05_black.png"],"assets/icons/3.5x/bottom_splash.png":["assets/icons/3.5x/bottom_splash.png"],"assets/icons/3.5x/icon_15back-black.png":["assets/icons/3.5x/icon_15back-black.png"],"assets/icons/3.5x/icon_15back-light.png":["assets/icons/3.5x/icon_15back-light.png"],"assets/icons/3.5x/icon_15forward-black.png":["assets/icons/3.5x/icon_15forward-black.png"],"assets/icons/3.5x/icon_15forward-light.png":["assets/icons/3.5x/icon_15forward-light.png"],"assets/icons/3.5x/icon_UPS.png":["assets/icons/3.5x/icon_UPS.png"],"assets/icons/3.5x/icon_collapse.png":["assets/icons/3.5x/icon_collapse.png"],"assets/icons/3.5x/icon_footnote_arrow.png":["assets/icons/3.5x/icon_footnote_arrow.png"],"assets/icons/3.5x/icon_forward-black.png":["assets/icons/3.5x/icon_forward-black.png"],"assets/icons/3.5x/icon_forward-light.png":["assets/icons/3.5x/icon_forward-light.png"],"assets/icons/3.5x/icon_live-gold.png":["assets/icons/3.5x/icon_live-gold.png"],"assets/icons/3.5x/icon_live-red.png":["assets/icons/3.5x/icon_live-red.png"],"assets/icons/3.5x/icon_live-white.png":["assets/icons/3.5x/icon_live-white.png"],"assets/icons/3.5x/icon_ok-black.png":["assets/icons/3.5x/icon_ok-black.png"],"assets/icons/3.5x/icon_ok-light.png":["assets/icons/3.5x/icon_ok-light.png"],"assets/icons/3.5x/icon_profile.png":["assets/icons/3.5x/icon_profile.png"],"assets/icons/3.5x/icon_search.png":["assets/icons/3.5x/icon_search.png"],"assets/icons/3.5x/logo.png":["assets/icons/3.5x/logo.png"],"assets/icons/3.5x/story_logo-black.png":["assets/icons/3.5x/story_logo-black.png"],"assets/icons/3.5x/story_logo-light.png":["assets/icons/3.5x/story_logo-light.png"],"assets/icons/3.5x/top_splash.png":["assets/icons/3.5x/top_splash.png"],"assets/icons/app_icon_1.png":["assets/icons/app_icon_1.png"],"assets/icons/app_icon_10.png":["assets/icons/app_icon_10.png"],"assets/icons/app_icon_11.png":["assets/icons/app_icon_11.png"],"assets/icons/app_icon_12.png":["assets/icons/app_icon_12.png"],"assets/icons/app_icon_13.png":["assets/icons/app_icon_13.png"],"assets/icons/app_icon_14.png":["assets/icons/app_icon_14.png"],"assets/icons/app_icon_15.png":["assets/icons/app_icon_15.png"],"assets/icons/app_icon_16.png":["assets/icons/app_icon_16.png"],"assets/icons/app_icon_17.png":["assets/icons/app_icon_17.png"],"assets/icons/app_icon_18.png":["assets/icons/app_icon_18.png"],"assets/icons/app_icon_19.png":["assets/icons/app_icon_19.png"],"assets/icons/app_icon_4.png":["assets/icons/app_icon_4.png"],"assets/icons/app_icon_5.png":["assets/icons/app_icon_5.png"],"assets/icons/app_icon_6.png":["assets/icons/app_icon_6.png"],"assets/icons/app_icon_7.png":["assets/icons/app_icon_7.png"],"assets/icons/app_icon_8.png":["assets/icons/app_icon_8.png"],"assets/icons/app_icon_9.png":["assets/icons/app_icon_9.png"],"assets/icons/banner_bg.png":["assets/icons/banner_bg.png","assets/icons/2x/banner_bg.png","assets/icons/3.5x/banner_bg.png"],"assets/icons/banner_thanks.png":["assets/icons/banner_thanks.png","assets/icons/2x/banner_thanks.png","assets/icons/3.5x/banner_thanks.png"],"assets/icons/bg_footnote-black.png":["assets/icons/bg_footnote-black.png","assets/icons/2x/bg_footnote-black.png","assets/icons/3.5x/bg_footnote-black.png"],"assets/icons/bg_footnote-light.png":["assets/icons/bg_footnote-light.png","assets/icons/2x/bg_footnote-light.png","assets/icons/3.5x/bg_footnote-light.png"],"assets/icons/bg_heaven_01.png":["assets/icons/bg_heaven_01.png","assets/icons/2x/bg_heaven_01.png","assets/icons/3.5x/bg_heaven_01.png"],"assets/icons/bg_heaven_01_black.png":["assets/icons/bg_heaven_01_black.png","assets/icons/2x/bg_heaven_01_black.png","assets/icons/3.5x/bg_heaven_01_black.png"],"assets/icons/bg_heaven_02.png":["assets/icons/bg_heaven_02.png","assets/icons/2x/bg_heaven_02.png","assets/icons/3.5x/bg_heaven_02.png"],"assets/icons/bg_heaven_02_black.png":["assets/icons/bg_heaven_02_black.png","assets/icons/2x/bg_heaven_02_black.png","assets/icons/3.5x/bg_heaven_02_black.png"],"assets/icons/bg_heaven_03.png":["assets/icons/bg_heaven_03.png","assets/icons/2x/bg_heaven_03.png","assets/icons/3.5x/bg_heaven_03.png"],"assets/icons/bg_heaven_03_black.png":["assets/icons/bg_heaven_03_black.png","assets/icons/2x/bg_heaven_03_black.png","assets/icons/3.5x/bg_heaven_03_black.png"],"assets/icons/bg_heaven_04.png":["assets/icons/bg_heaven_04.png","assets/icons/2x/bg_heaven_04.png","assets/icons/3.5x/bg_heaven_04.png"],"assets/icons/bg_heaven_04_black.png":["assets/icons/bg_heaven_04_black.png","assets/icons/2x/bg_heaven_04_black.png","assets/icons/3.5x/bg_heaven_04_black.png"],"assets/icons/bg_heaven_05.png":["assets/icons/bg_heaven_05.png","assets/icons/2x/bg_heaven_05.png","assets/icons/3.5x/bg_heaven_05.png"],"assets/icons/bg_heaven_05_black.png":["assets/icons/bg_heaven_05_black.png","assets/icons/2x/bg_heaven_05_black.png","assets/icons/3.5x/bg_heaven_05_black.png"],"assets/icons/bg_hell_01.png":["assets/icons/bg_hell_01.png","assets/icons/2x/bg_hell_01.png","assets/icons/3.5x/bg_hell_01.png"],"assets/icons/bg_hell_01_black.png":["assets/icons/bg_hell_01_black.png","assets/icons/2x/bg_hell_01_black.png","assets/icons/3.5x/bg_hell_01_black.png"],"assets/icons/bg_hell_02.png":["assets/icons/bg_hell_02.png","assets/icons/2x/bg_hell_02.png","assets/icons/3.5x/bg_hell_02.png"],"assets/icons/bg_hell_02_black.png":["assets/icons/bg_hell_02_black.png","assets/icons/2x/bg_hell_02_black.png","assets/icons/3.5x/bg_hell_02_black.png"],"assets/icons/bg_hell_03.png":["assets/icons/bg_hell_03.png","assets/icons/2x/bg_hell_03.png","assets/icons/3.5x/bg_hell_03.png"],"assets/icons/bg_hell_03_black.png":["assets/icons/bg_hell_03_black.png","assets/icons/2x/bg_hell_03_black.png","assets/icons/3.5x/bg_hell_03_black.png"],"assets/icons/bg_hell_04.png":["assets/icons/bg_hell_04.png","assets/icons/2x/bg_hell_04.png","assets/icons/3.5x/bg_hell_04.png"],"assets/icons/bg_hell_04_black.png":["assets/icons/bg_hell_04_black.png","assets/icons/2x/bg_hell_04_black.png","assets/icons/3.5x/bg_hell_04_black.png"],"assets/icons/bg_hell_05.png":["assets/icons/bg_hell_05.png","assets/icons/2x/bg_hell_05.png","assets/icons/3.5x/bg_hell_05.png"],"assets/icons/bg_hell_05_black.png":["assets/icons/bg_hell_05_black.png","assets/icons/2x/bg_hell_05_black.png","assets/icons/3.5x/bg_hell_05_black.png"],"assets/icons/bg_hell_AD_05.png":["assets/icons/bg_hell_AD_05.png","assets/icons/2x/bg_hell_AD_05.png","assets/icons/3.5x/bg_hell_AD_05.png"],"assets/icons/bg_hell_AD_05_black.png":["assets/icons/bg_hell_AD_05_black.png","assets/icons/2x/bg_hell_AD_05_black.png","assets/icons/3.5x/bg_hell_AD_05_black.png"],"assets/icons/bottom_splash.png":["assets/icons/bottom_splash.png","assets/icons/2x/bottom_splash.png","assets/icons/3.5x/bottom_splash.png"],"assets/icons/error_image_black.png":["assets/icons/error_image_black.png"],"assets/icons/error_image_light.png":["assets/icons/error_image_light.png"],"assets/icons/icon_15back-black.png":["assets/icons/icon_15back-black.png","assets/icons/2x/icon_15back-black.png","assets/icons/3.5x/icon_15back-black.png"],"assets/icons/icon_15back-light.png":["assets/icons/icon_15back-light.png","assets/icons/2x/icon_15back-light.png","assets/icons/3.5x/icon_15back-light.png"],"assets/icons/icon_15forward-black.png":["assets/icons/icon_15forward-black.png","assets/icons/2x/icon_15forward-black.png","assets/icons/3.5x/icon_15forward-black.png"],"assets/icons/icon_15forward-light.png":["assets/icons/icon_15forward-light.png","assets/icons/2x/icon_15forward-light.png","assets/icons/3.5x/icon_15forward-light.png"],"assets/icons/icon_UPS.png":["assets/icons/icon_UPS.png","assets/icons/2x/icon_UPS.png","assets/icons/3.5x/icon_UPS.png"],"assets/icons/icon_bookmarks-black.png":["assets/icons/icon_bookmarks-black.png"],"assets/icons/icon_bookmarks-light.png":["assets/icons/icon_bookmarks-light.png"],"assets/icons/icon_collapse.png":["assets/icons/icon_collapse.png","assets/icons/2x/icon_collapse.png","assets/icons/3.5x/icon_collapse.png"],"assets/icons/icon_footnote_arrow.png":["assets/icons/icon_footnote_arrow.png","assets/icons/2x/icon_footnote_arrow.png","assets/icons/3.5x/icon_footnote_arrow.png"],"assets/icons/icon_forward-black.png":["assets/icons/icon_forward-black.png","assets/icons/2x/icon_forward-black.png","assets/icons/3.5x/icon_forward-black.png"],"assets/icons/icon_forward-light.png":["assets/icons/icon_forward-light.png","assets/icons/2x/icon_forward-light.png","assets/icons/3.5x/icon_forward-light.png"],"assets/icons/icon_live-gold.png":["assets/icons/icon_live-gold.png","assets/icons/2x/icon_live-gold.png","assets/icons/3.5x/icon_live-gold.png"],"assets/icons/icon_live-red.png":["assets/icons/icon_live-red.png","assets/icons/2x/icon_live-red.png","assets/icons/3.5x/icon_live-red.png"],"assets/icons/icon_live-white.png":["assets/icons/icon_live-white.png","assets/icons/2x/icon_live-white.png","assets/icons/3.5x/icon_live-white.png"],"assets/icons/icon_my_books-black.png":["assets/icons/icon_my_books-black.png"],"assets/icons/icon_my_books-light.png":["assets/icons/icon_my_books-light.png"],"assets/icons/icon_ok-black.png":["assets/icons/icon_ok-black.png","assets/icons/2x/icon_ok-black.png","assets/icons/3.5x/icon_ok-black.png"],"assets/icons/icon_ok-light.png":["assets/icons/icon_ok-light.png","assets/icons/2x/icon_ok-light.png","assets/icons/3.5x/icon_ok-light.png"],"assets/icons/icon_podcasts-black.png":["assets/icons/icon_podcasts-black.png"],"assets/icons/icon_podcasts-light.png":["assets/icons/icon_podcasts-light.png"],"assets/icons/icon_profile.png":["assets/icons/icon_profile.png","assets/icons/2x/icon_profile.png","assets/icons/3.5x/icon_profile.png"],"assets/icons/icon_search.png":["assets/icons/icon_search.png","assets/icons/2x/icon_search.png","assets/icons/3.5x/icon_search.png"],"assets/icons/icon_search_screen-black.png":["assets/icons/icon_search_screen-black.png"],"assets/icons/icon_search_screen-light.png":["assets/icons/icon_search_screen-light.png"],"assets/icons/icon_shop-black.png":["assets/icons/icon_shop-black.png"],"assets/icons/icon_shop-light.png":["assets/icons/icon_shop-light.png"],"assets/icons/logo.png":["assets/icons/logo.png","assets/icons/2x/logo.png","assets/icons/3.5x/logo.png"],"assets/icons/story_logo-black.png":["assets/icons/story_logo-black.png","assets/icons/2x/story_logo-black.png","assets/icons/3.5x/story_logo-black.png"],"assets/icons/story_logo-light.png":["assets/icons/story_logo-light.png","assets/icons/2x/story_logo-light.png","assets/icons/3.5x/story_logo-light.png"],"assets/icons/top_splash.png":["assets/icons/top_splash.png","assets/icons/2x/top_splash.png","assets/icons/3.5x/top_splash.png"],"assets/icons/yt_icon_mono_light.png":["assets/icons/yt_icon_mono_light.png"],"assets/images/onboarding/book_offer.svg":["assets/images/onboarding/book_offer.svg"],"assets/images/onboarding/gradient_blue_center_top.webp":["assets/images/onboarding/gradient_blue_center_top.webp"],"assets/images/onboarding/gradient_blue_green_top_right.webp":["assets/images/onboarding/gradient_blue_green_top_right.webp"],"assets/images/onboarding/gradient_blue_right_down.webp":["assets/images/onboarding/gradient_blue_right_down.webp"],"assets/images/onboarding/gradient_orange_center_left.webp":["assets/images/onboarding/gradient_orange_center_left.webp"],"assets/images/onboarding/gradient_orange_down_left.webp":["assets/images/onboarding/gradient_orange_down_left.webp"],"assets/rive/book_icon.flr":["assets/rive/book_icon.flr"],"assets/rive/bookmark.flr":["assets/rive/bookmark.flr"],"assets/rive/buffering.flr":["assets/rive/buffering.flr"],"assets/rive/instagram.flr":["assets/rive/instagram.flr"],"assets/rive/podcast.flr":["assets/rive/podcast.flr"],"assets/svg-icons/bg_footnote.svg":["assets/svg-icons/bg_footnote.svg"],"assets/svg-icons/icon_112xscore.svg":["assets/svg-icons/icon_112xscore.svg"],"assets/svg-icons/icon_12xscore.svg":["assets/svg-icons/icon_12xscore.svg"],"assets/svg-icons/icon_15back.svg":["assets/svg-icons/icon_15back.svg"],"assets/svg-icons/icon_15forward.svg":["assets/svg-icons/icon_15forward.svg"],"assets/svg-icons/icon_1xscore.svg":["assets/svg-icons/icon_1xscore.svg"],"assets/svg-icons/icon_2xscore.svg":["assets/svg-icons/icon_2xscore.svg"],"assets/svg-icons/icon_apple.svg":["assets/svg-icons/icon_apple.svg"],"assets/svg-icons/icon_arrow-grey.svg":["assets/svg-icons/icon_arrow-grey.svg"],"assets/svg-icons/icon_arrow.svg":["assets/svg-icons/icon_arrow.svg"],"assets/svg-icons/icon_arrow_down.svg":["assets/svg-icons/icon_arrow_down.svg"],"assets/svg-icons/icon_back-arrow.svg":["assets/svg-icons/icon_back-arrow.svg"],"assets/svg-icons/icon_back.svg":["assets/svg-icons/icon_back.svg"],"assets/svg-icons/icon_back_to_feed.svg":["assets/svg-icons/icon_back_to_feed.svg"],"assets/svg-icons/icon_beta-material.svg":["assets/svg-icons/icon_beta-material.svg"],"assets/svg-icons/icon_book_feed.svg":["assets/svg-icons/icon_book_feed.svg"],"assets/svg-icons/icon_book_settings.svg":["assets/svg-icons/icon_book_settings.svg"],"assets/svg-icons/icon_bookmark-active.svg":["assets/svg-icons/icon_bookmark-active.svg"],"assets/svg-icons/icon_bookmark-feed-active.svg":["assets/svg-icons/icon_bookmark-feed-active.svg"],"assets/svg-icons/icon_bookmark-feed-inactive.svg":["assets/svg-icons/icon_bookmark-feed-inactive.svg"],"assets/svg-icons/icon_bookmark-inactive.svg":["assets/svg-icons/icon_bookmark-inactive.svg"],"assets/svg-icons/icon_bookmark-loader.svg":["assets/svg-icons/icon_bookmark-loader.svg"],"assets/svg-icons/icon_bookmarkBig.svg":["assets/svg-icons/icon_bookmarkBig.svg"],"assets/svg-icons/icon_brightness_high.svg":["assets/svg-icons/icon_brightness_high.svg"],"assets/svg-icons/icon_brightness_low.svg":["assets/svg-icons/icon_brightness_low.svg"],"assets/svg-icons/icon_button-minus.svg":["assets/svg-icons/icon_button-minus.svg"],"assets/svg-icons/icon_button-plus.svg":["assets/svg-icons/icon_button-plus.svg"],"assets/svg-icons/icon_cache_informer.svg":["assets/svg-icons/icon_cache_informer.svg"],"assets/svg-icons/icon_cache_not_saved.svg":["assets/svg-icons/icon_cache_not_saved.svg"],"assets/svg-icons/icon_cache_saved.svg":["assets/svg-icons/icon_cache_saved.svg"],"assets/svg-icons/icon_cards.svg":["assets/svg-icons/icon_cards.svg"],"assets/svg-icons/icon_check_mark.svg":["assets/svg-icons/icon_check_mark.svg"],"assets/svg-icons/icon_close-mini.svg":["assets/svg-icons/icon_close-mini.svg"],"assets/svg-icons/icon_close.svg":["assets/svg-icons/icon_close.svg"],"assets/svg-icons/icon_close_book_player.svg":["assets/svg-icons/icon_close_book_player.svg"],"assets/svg-icons/icon_download-feed.svg":["assets/svg-icons/icon_download-feed.svg"],"assets/svg-icons/icon_download_circle.svg":["assets/svg-icons/icon_download_circle.svg"],"assets/svg-icons/icon_fb.svg":["assets/svg-icons/icon_fb.svg"],"assets/svg-icons/icon_feed.svg":["assets/svg-icons/icon_feed.svg"],"assets/svg-icons/icon_forward.svg":["assets/svg-icons/icon_forward.svg"],"assets/svg-icons/icon_google.svg":["assets/svg-icons/icon_google.svg"],"assets/svg-icons/icon_headers.svg":["assets/svg-icons/icon_headers.svg"],"assets/svg-icons/icon_home.svg":["assets/svg-icons/icon_home.svg"],"assets/svg-icons/icon_info.svg":["assets/svg-icons/icon_info.svg"],"assets/svg-icons/icon_instagram.svg":["assets/svg-icons/icon_instagram.svg"],"assets/svg-icons/icon_launch_link.svg":["assets/svg-icons/icon_launch_link.svg"],"assets/svg-icons/icon_line_height_l.svg":["assets/svg-icons/icon_line_height_l.svg"],"assets/svg-icons/icon_line_height_m.svg":["assets/svg-icons/icon_line_height_m.svg"],"assets/svg-icons/icon_line_height_s.svg":["assets/svg-icons/icon_line_height_s.svg"],"assets/svg-icons/icon_listened.svg":["assets/svg-icons/icon_listened.svg"],"assets/svg-icons/icon_magic_link.svg":["assets/svg-icons/icon_magic_link.svg"],"assets/svg-icons/icon_margin_l.svg":["assets/svg-icons/icon_margin_l.svg"],"assets/svg-icons/icon_margin_m.svg":["assets/svg-icons/icon_margin_m.svg"],"assets/svg-icons/icon_margin_s.svg":["assets/svg-icons/icon_margin_s.svg"],"assets/svg-icons/icon_oil.svg":["assets/svg-icons/icon_oil.svg"],"assets/svg-icons/icon_ok.svg":["assets/svg-icons/icon_ok.svg"],"assets/svg-icons/icon_pause-feed.svg":["assets/svg-icons/icon_pause-feed.svg"],"assets/svg-icons/icon_pause-large.svg":["assets/svg-icons/icon_pause-large.svg"],"assets/svg-icons/icon_pause-small.svg":["assets/svg-icons/icon_pause-small.svg"],"assets/svg-icons/icon_pause_default.svg":["assets/svg-icons/icon_pause_default.svg"],"assets/svg-icons/icon_pause_default_progress.svg":["assets/svg-icons/icon_pause_default_progress.svg"],"assets/svg-icons/icon_pause_player_popup.svg":["assets/svg-icons/icon_pause_player_popup.svg"],"assets/svg-icons/icon_pdf.svg":["assets/svg-icons/icon_pdf.svg"],"assets/svg-icons/icon_play-feed.svg":["assets/svg-icons/icon_play-feed.svg"],"assets/svg-icons/icon_play-large.svg":["assets/svg-icons/icon_play-large.svg"],"assets/svg-icons/icon_play-small.svg":["assets/svg-icons/icon_play-small.svg"],"assets/svg-icons/icon_play_default.svg":["assets/svg-icons/icon_play_default.svg"],"assets/svg-icons/icon_play_default_progress.svg":["assets/svg-icons/icon_play_default_progress.svg"],"assets/svg-icons/icon_play_player_popup.svg":["assets/svg-icons/icon_play_player_popup.svg"],"assets/svg-icons/icon_podcast-bookmark-active.svg":["assets/svg-icons/icon_podcast-bookmark-active.svg"],"assets/svg-icons/icon_podcast-bookmark-inactive.svg":["assets/svg-icons/icon_podcast-bookmark-inactive.svg"],"assets/svg-icons/icon_podcast-download-error.svg":["assets/svg-icons/icon_podcast-download-error.svg"],"assets/svg-icons/icon_podcast-download.svg":["assets/svg-icons/icon_podcast-download.svg"],"assets/svg-icons/icon_podcast-material.svg":["assets/svg-icons/icon_podcast-material.svg"],"assets/svg-icons/icon_podcasts_feed.svg":["assets/svg-icons/icon_podcasts_feed.svg"],"assets/svg-icons/icon_poll-checkbox.svg":["assets/svg-icons/icon_poll-checkbox.svg"],"assets/svg-icons/icon_read.svg":["assets/svg-icons/icon_read.svg"],"assets/svg-icons/icon_remove_book.svg":["assets/svg-icons/icon_remove_book.svg"],"assets/svg-icons/icon_save_book.svg":["assets/svg-icons/icon_save_book.svg"],"assets/svg-icons/icon_search_book.svg":["assets/svg-icons/icon_search_book.svg"],"assets/svg-icons/icon_search_input.svg":["assets/svg-icons/icon_search_input.svg"],"assets/svg-icons/icon_second.svg":["assets/svg-icons/icon_second.svg"],"assets/svg-icons/icon_settings.svg":["assets/svg-icons/icon_settings.svg"],"assets/svg-icons/icon_settings_bug.svg":["assets/svg-icons/icon_settings_bug.svg"],"assets/svg-icons/icon_settings_caches.svg":["assets/svg-icons/icon_settings_caches.svg"],"assets/svg-icons/icon_settings_fb.svg":["assets/svg-icons/icon_settings_fb.svg"],"assets/svg-icons/icon_settings_feedate.svg":["assets/svg-icons/icon_settings_feedate.svg"],"assets/svg-icons/icon_settings_instagram.svg":["assets/svg-icons/icon_settings_instagram.svg"],"assets/svg-icons/icon_settings_mail.svg":["assets/svg-icons/icon_settings_mail.svg"],"assets/svg-icons/icon_settings_meduza.svg":["assets/svg-icons/icon_settings_meduza.svg"],"assets/svg-icons/icon_settings_night.svg":["assets/svg-icons/icon_settings_night.svg"],"assets/svg-icons/icon_settings_podcast.svg":["assets/svg-icons/icon_settings_podcast.svg"],"assets/svg-icons/icon_settings_profile.svg":["assets/svg-icons/icon_settings_profile.svg"],"assets/svg-icons/icon_settings_push.svg":["assets/svg-icons/icon_settings_push.svg"],"assets/svg-icons/icon_settings_telegram.svg":["assets/svg-icons/icon_settings_telegram.svg"],"assets/svg-icons/icon_settings_text.svg":["assets/svg-icons/icon_settings_text.svg"],"assets/svg-icons/icon_settings_twitter.svg":["assets/svg-icons/icon_settings_twitter.svg"],"assets/svg-icons/icon_settings_vk.svg":["assets/svg-icons/icon_settings_vk.svg"],"assets/svg-icons/icon_settings_youtube.svg":["assets/svg-icons/icon_settings_youtube.svg"],"assets/svg-icons/icon_share-feed.svg":["assets/svg-icons/icon_share-feed.svg"],"assets/svg-icons/icon_share.svg":["assets/svg-icons/icon_share.svg"],"assets/svg-icons/icon_stories-left.svg":["assets/svg-icons/icon_stories-left.svg"],"assets/svg-icons/icon_stories-right.svg":["assets/svg-icons/icon_stories-right.svg"],"assets/svg-icons/icon_twitter.svg":["assets/svg-icons/icon_twitter.svg"],"assets/svg-icons/icon_video.svg":["assets/svg-icons/icon_video.svg"],"assets/svg-icons/push_lightning.svg":["assets/svg-icons/push_lightning.svg"],"assets/svg/bg_footnote-black.svg":["assets/svg/bg_footnote-black.svg"],"assets/svg/bg_footnote-light.svg":["assets/svg/bg_footnote-light.svg"],"assets/svg/icon_112xscore-black.svg":["assets/svg/icon_112xscore-black.svg"],"assets/svg/icon_112xscore-light.svg":["assets/svg/icon_112xscore-light.svg"],"assets/svg/icon_12xscore-black.svg":["assets/svg/icon_12xscore-black.svg"],"assets/svg/icon_12xscore-light.svg":["assets/svg/icon_12xscore-light.svg"],"assets/svg/icon_15back-black.svg":["assets/svg/icon_15back-black.svg"],"assets/svg/icon_15back-light.svg":["assets/svg/icon_15back-light.svg"],"assets/svg/icon_15forward-black.svg":["assets/svg/icon_15forward-black.svg"],"assets/svg/icon_15forward-light.svg":["assets/svg/icon_15forward-light.svg"],"assets/svg/icon_1xscore-black.svg":["assets/svg/icon_1xscore-black.svg"],"assets/svg/icon_1xscore-light.svg":["assets/svg/icon_1xscore-light.svg"],"assets/svg/icon_2xscore-black.svg":["assets/svg/icon_2xscore-black.svg"],"assets/svg/icon_2xscore-light.svg":["assets/svg/icon_2xscore-light.svg"],"assets/svg/icon_UPS.svg":["assets/svg/icon_UPS.svg"],"assets/svg/icon_apple-black.svg":["assets/svg/icon_apple-black.svg"],"assets/svg/icon_apple-light.svg":["assets/svg/icon_apple-light.svg"],"assets/svg/icon_arrow-black.svg":["assets/svg/icon_arrow-black.svg"],"assets/svg/icon_arrow-grey-light.svg":["assets/svg/icon_arrow-grey-light.svg"],"assets/svg/icon_arrow-light.svg":["assets/svg/icon_arrow-light.svg"],"assets/svg/icon_back-arrow-black.svg":["assets/svg/icon_back-arrow-black.svg"],"assets/svg/icon_back-arrow-light.svg":["assets/svg/icon_back-arrow-light.svg"],"assets/svg/icon_back-black.svg":["assets/svg/icon_back-black.svg"],"assets/svg/icon_back-light.svg":["assets/svg/icon_back-light.svg"],"assets/svg/icon_beta-active.svg":["assets/svg/icon_beta-active.svg"],"assets/svg/icon_beta-inactive.svg":["assets/svg/icon_beta-inactive.svg"],"assets/svg/icon_beta-material-black.svg":["assets/svg/icon_beta-material-black.svg"],"assets/svg/icon_beta-material-light.svg":["assets/svg/icon_beta-material-light.svg"],"assets/svg/icon_bookmark-active-black.svg":["assets/svg/icon_bookmark-active-black.svg"],"assets/svg/icon_bookmark-active-light.svg":["assets/svg/icon_bookmark-active-light.svg"],"assets/svg/icon_bookmark-feed-active-black.svg":["assets/svg/icon_bookmark-feed-active-black.svg"],"assets/svg/icon_bookmark-feed-active-light.svg":["assets/svg/icon_bookmark-feed-active-light.svg"],"assets/svg/icon_bookmark-feed-inactive-black.svg":["assets/svg/icon_bookmark-feed-inactive-black.svg"],"assets/svg/icon_bookmark-feed-inactive-light.svg":["assets/svg/icon_bookmark-feed-inactive-light.svg"],"assets/svg/icon_bookmark-inactive-black.svg":["assets/svg/icon_bookmark-inactive-black.svg"],"assets/svg/icon_bookmark-inactive-light.svg":["assets/svg/icon_bookmark-inactive-light.svg"],"assets/svg/icon_bookmark-loader-black.svg":["assets/svg/icon_bookmark-loader-black.svg"],"assets/svg/icon_bookmark-loader-light.svg":["assets/svg/icon_bookmark-loader-light.svg"],"assets/svg/icon_button-minus-black.svg":["assets/svg/icon_button-minus-black.svg"],"assets/svg/icon_button-minus-light.svg":["assets/svg/icon_button-minus-light.svg"],"assets/svg/icon_button-plus-black.svg":["assets/svg/icon_button-plus-black.svg"],"assets/svg/icon_button-plus-light.svg":["assets/svg/icon_button-plus-light.svg"],"assets/svg/icon_cache_not_saved_black.svg":["assets/svg/icon_cache_not_saved_black.svg"],"assets/svg/icon_cache_not_saved_light.svg":["assets/svg/icon_cache_not_saved_light.svg"],"assets/svg/icon_cache_saved.svg":["assets/svg/icon_cache_saved.svg"],"assets/svg/icon_cards-black.svg":["assets/svg/icon_cards-black.svg"],"assets/svg/icon_cards-light.svg":["assets/svg/icon_cards-light.svg"],"assets/svg/icon_close-black.svg":["assets/svg/icon_close-black.svg"],"assets/svg/icon_close-light.svg":["assets/svg/icon_close-light.svg"],"assets/svg/icon_close-mini-black.svg":["assets/svg/icon_close-mini-black.svg"],"assets/svg/icon_close-mini-light.svg":["assets/svg/icon_close-mini-light.svg"],"assets/svg/icon_credit.svg":["assets/svg/icon_credit.svg"],"assets/svg/icon_download-feed-black.svg":["assets/svg/icon_download-feed-black.svg"],"assets/svg/icon_download-feed-light.svg":["assets/svg/icon_download-feed-light.svg"],"assets/svg/icon_external.svg":["assets/svg/icon_external.svg"],"assets/svg/icon_external_gold.svg":["assets/svg/icon_external_gold.svg"],"assets/svg/icon_fb-black.svg":["assets/svg/icon_fb-black.svg"],"assets/svg/icon_fb-light.svg":["assets/svg/icon_fb-light.svg"],"assets/svg/icon_forward-black.svg":["assets/svg/icon_forward-black.svg"],"assets/svg/icon_forward-light.svg":["assets/svg/icon_forward-light.svg"],"assets/svg/icon_google-black.svg":["assets/svg/icon_google-black.svg"],"assets/svg/icon_google-light.svg":["assets/svg/icon_google-light.svg"],"assets/svg/icon_info-black.svg":["assets/svg/icon_info-black.svg"],"assets/svg/icon_info-light.svg":["assets/svg/icon_info-light.svg"],"assets/svg/icon_instagram-black.svg":["assets/svg/icon_instagram-black.svg"],"assets/svg/icon_instagram-light.svg":["assets/svg/icon_instagram-light.svg"],"assets/svg/icon_listened-black.svg":["assets/svg/icon_listened-black.svg"],"assets/svg/icon_listened-light.svg":["assets/svg/icon_listened-light.svg"],"assets/svg/icon_live-gold.svg":["assets/svg/icon_live-gold.svg"],"assets/svg/icon_live-red.svg":["assets/svg/icon_live-red.svg"],"assets/svg/icon_meta-trusted.svg":["assets/svg/icon_meta-trusted.svg"],"assets/svg/icon_meta-untrusted.svg":["assets/svg/icon_meta-untrusted.svg"],"assets/svg/icon_meta-whoknows.svg":["assets/svg/icon_meta-whoknows.svg"],"assets/svg/icon_oil-black.svg":["assets/svg/icon_oil-black.svg"],"assets/svg/icon_oil-light.svg":["assets/svg/icon_oil-light.svg"],"assets/svg/icon_ok-black.svg":["assets/svg/icon_ok-black.svg"],"assets/svg/icon_ok-light.svg":["assets/svg/icon_ok-light.svg"],"assets/svg/icon_pause-feed.svg":["assets/svg/icon_pause-feed.svg"],"assets/svg/icon_pause-large-black.svg":["assets/svg/icon_pause-large-black.svg"],"assets/svg/icon_pause-large-light.svg":["assets/svg/icon_pause-large-light.svg"],"assets/svg/icon_pause-large-white.svg":["assets/svg/icon_pause-large-white.svg"],"assets/svg/icon_pause-small-black.svg":["assets/svg/icon_pause-small-black.svg"],"assets/svg/icon_pause-small-light.svg":["assets/svg/icon_pause-small-light.svg"],"assets/svg/icon_play-feed.svg":["assets/svg/icon_play-feed.svg"],"assets/svg/icon_play-large-black.svg":["assets/svg/icon_play-large-black.svg"],"assets/svg/icon_play-large-light.svg":["assets/svg/icon_play-large-light.svg"],"assets/svg/icon_play-large-white-noCircle.svg":["assets/svg/icon_play-large-white-noCircle.svg"],"assets/svg/icon_play-large-white.svg":["assets/svg/icon_play-large-white.svg"],"assets/svg/icon_play-small-black.svg":["assets/svg/icon_play-small-black.svg"],"assets/svg/icon_play-small-light.svg":["assets/svg/icon_play-small-light.svg"],"assets/svg/icon_podcast-active.svg":["assets/svg/icon_podcast-active.svg"],"assets/svg/icon_podcast-bookmark-active-black.svg":["assets/svg/icon_podcast-bookmark-active-black.svg"],"assets/svg/icon_podcast-bookmark-active-light.svg":["assets/svg/icon_podcast-bookmark-active-light.svg"],"assets/svg/icon_podcast-bookmark-inactive-black.svg":["assets/svg/icon_podcast-bookmark-inactive-black.svg"],"assets/svg/icon_podcast-bookmark-inactive-light.svg":["assets/svg/icon_podcast-bookmark-inactive-light.svg"],"assets/svg/icon_podcast-download-black.svg":["assets/svg/icon_podcast-download-black.svg"],"assets/svg/icon_podcast-download-light.svg":["assets/svg/icon_podcast-download-light.svg"],"assets/svg/icon_podcast-inactive.svg":["assets/svg/icon_podcast-inactive.svg"],"assets/svg/icon_podcast-material-black.svg":["assets/svg/icon_podcast-material-black.svg"],"assets/svg/icon_podcast-material-light.svg":["assets/svg/icon_podcast-material-light.svg"],"assets/svg/icon_profile.svg":["assets/svg/icon_profile.svg"],"assets/svg/icon_read-black.svg":["assets/svg/icon_read-black.svg"],"assets/svg/icon_read-light.svg":["assets/svg/icon_read-light.svg"],"assets/svg/icon_search.svg":["assets/svg/icon_search.svg"],"assets/svg/icon_second_star.svg":["assets/svg/icon_second_star.svg"],"assets/svg/icon_share-black.svg":["assets/svg/icon_share-black.svg"],"assets/svg/icon_share-feed-black.svg":["assets/svg/icon_share-feed-black.svg"],"assets/svg/icon_share-feed-light.svg":["assets/svg/icon_share-feed-light.svg"],"assets/svg/icon_share-light.svg":["assets/svg/icon_share-light.svg"],"assets/svg/icon_stories-left-black.svg":["assets/svg/icon_stories-left-black.svg"],"assets/svg/icon_stories-left-light.svg":["assets/svg/icon_stories-left-light.svg"],"assets/svg/icon_stories-right-black.svg":["assets/svg/icon_stories-right-black.svg"],"assets/svg/icon_stories-right-light.svg":["assets/svg/icon_stories-right-light.svg"],"assets/svg/icon_twitter-black.svg":["assets/svg/icon_twitter-black.svg"],"assets/svg/icon_twitter-light.svg":["assets/svg/icon_twitter-light.svg"],"assets/svg/icon_video-black.svg":["assets/svg/icon_video-black.svg"],"assets/svg/icon_video-light.svg":["assets/svg/icon_video-light.svg"],"assets/svg/logo_splash.svg":["assets/svg/logo_splash.svg"],"assets/svg/push_lightning-black.svg":["assets/svg/push_lightning-black.svg"],"assets/svg/push_lightning-light.svg":["assets/svg/push_lightning-light.svg"],"packages/cupertino_icons/assets/CupertinoIcons.ttf":["packages/cupertino_icons/assets/CupertinoIcons.ttf"],"packages/flutter_inappwebview/assets/t_rex_runner/t-rex.css":["packages/flutter_inappwebview/assets/t_rex_runner/t-rex.css"],"packages/flutter_inappwebview/assets/t_rex_runner/t-rex.html":["packages/flutter_inappwebview/assets/t_rex_runner/t-rex.html"],"packages/flutter_inappwebview_web/assets/web/web_support.js":["packages/flutter_inappwebview_web/assets/web/web_support.js"],"packages/golden_toolkit/fonts/Roboto-Regular.ttf":["packages/golden_toolkit/fonts/Roboto-Regular.ttf"],"packages/tweet_ui/assets/1.5x/tw__ic_gif_badge.png":["packages/tweet_ui/assets/1.5x/tw__ic_gif_badge.png"],"packages/tweet_ui/assets/1.5x/tw__ic_logo_blue.png":["packages/tweet_ui/assets/1.5x/tw__ic_logo_blue.png"],"packages/tweet_ui/assets/1.5x/tw__ic_retweet_light.png":["packages/tweet_ui/assets/1.5x/tw__ic_retweet_light.png"],"packages/tweet_ui/assets/1.5x/tw__ic_tweet_verified.png":["packages/tweet_ui/assets/1.5x/tw__ic_tweet_verified.png"],"packages/tweet_ui/assets/2.0x/tw__ic_gif_badge.png":["packages/tweet_ui/assets/2.0x/tw__ic_gif_badge.png"],"packages/tweet_ui/assets/2.0x/tw__ic_logo_blue.png":["packages/tweet_ui/assets/2.0x/tw__ic_logo_blue.png"],"packages/tweet_ui/assets/2.0x/tw__ic_retweet_light.png":["packages/tweet_ui/assets/2.0x/tw__ic_retweet_light.png"],"packages/tweet_ui/assets/2.0x/tw__ic_tweet_verified.png":["packages/tweet_ui/assets/2.0x/tw__ic_tweet_verified.png"],"packages/tweet_ui/assets/3.0x/tw__ic_gif_badge.png":["packages/tweet_ui/assets/3.0x/tw__ic_gif_badge.png"],"packages/tweet_ui/assets/3.0x/tw__ic_logo_blue.png":["packages/tweet_ui/assets/3.0x/tw__ic_logo_blue.png"],"packages/tweet_ui/assets/3.0x/tw__ic_retweet_light.png":["packages/tweet_ui/assets/3.0x/tw__ic_retweet_light.png"],"packages/tweet_ui/assets/3.0x/tw__ic_tweet_verified.png":["packages/tweet_ui/assets/3.0x/tw__ic_tweet_verified.png"],"packages/tweet_ui/assets/tw__ic_gif_badge.png":["packages/tweet_ui/assets/tw__ic_gif_badge.png","packages/tweet_ui/assets/1.5x/tw__ic_gif_badge.png","packages/tweet_ui/assets/2.0x/tw__ic_gif_badge.png","packages/tweet_ui/assets/3.0x/tw__ic_gif_badge.png"],"packages/tweet_ui/assets/tw__ic_logo_blue.png":["packages/tweet_ui/assets/tw__ic_logo_blue.png","packages/tweet_ui/assets/1.5x/tw__ic_logo_blue.png","packages/tweet_ui/assets/2.0x/tw__ic_logo_blue.png","packages/tweet_ui/assets/3.0x/tw__ic_logo_blue.png"],"packages/tweet_ui/assets/tw__ic_retweet_light.png":["packages/tweet_ui/assets/tw__ic_retweet_light.png","packages/tweet_ui/assets/1.5x/tw__ic_retweet_light.png","packages/tweet_ui/assets/2.0x/tw__ic_retweet_light.png","packages/tweet_ui/assets/3.0x/tw__ic_retweet_light.png"],"packages/tweet_ui/assets/tw__ic_tweet_verified.png":["packages/tweet_ui/assets/tw__ic_tweet_verified.png","packages/tweet_ui/assets/1.5x/tw__ic_tweet_verified.png","packages/tweet_ui/assets/2.0x/tw__ic_tweet_verified.png","packages/tweet_ui/assets/3.0x/tw__ic_tweet_verified.png"],"packages/tweet_ui/fonts/Roboto-Black.ttf":["packages/tweet_ui/fonts/Roboto-Black.ttf"],"packages/tweet_ui/fonts/Roboto-BlackItalic.ttf":["packages/tweet_ui/fonts/Roboto-BlackItalic.ttf"],"packages/tweet_ui/fonts/Roboto-Bold.ttf":["packages/tweet_ui/fonts/Roboto-Bold.ttf"],"packages/tweet_ui/fonts/Roboto-BoldItalic.ttf":["packages/tweet_ui/fonts/Roboto-BoldItalic.ttf"],"packages/tweet_ui/fonts/Roboto-Light.ttf":["packages/tweet_ui/fonts/Roboto-Light.ttf"],"packages/tweet_ui/fonts/Roboto-LightItalic.ttf":["packages/tweet_ui/fonts/Roboto-LightItalic.ttf"],"packages/tweet_ui/fonts/Roboto-Medium.ttf":["packages/tweet_ui/fonts/Roboto-Medium.ttf"],"packages/tweet_ui/fonts/Roboto-MediumItalic.ttf":["packages/tweet_ui/fonts/Roboto-MediumItalic.ttf"],"packages/tweet_ui/fonts/Roboto-Regular.ttf":["packages/tweet_ui/fonts/Roboto-Regular.ttf"],"packages/tweet_ui/fonts/Roboto-RegularItalic.ttf":["packages/tweet_ui/fonts/Roboto-RegularItalic.ttf"],"packages/tweet_ui/fonts/Roboto-Thin.ttf":["packages/tweet_ui/fonts/Roboto-Thin.ttf"],"packages/tweet_ui/fonts/Roboto-ThinItalic.ttf":["packages/tweet_ui/fonts/Roboto-ThinItalic.ttf"],"packages/wakelock_plus/assets/no_sleep.js":["packages/wakelock_plus/assets/no_sleep.js"],"shorebird.yaml":["shorebird.yaml"]}